simple_worker/__init__.py
simple_worker/queue.py
simple_worker/task.py
simple_worker/task_executor.py
simple_worker/task_handler_registry.py
simple_worker/task_router.py
simple_worker/worker.py
simple_worker/queue_providers/__init__.py
simple_worker/queue_providers/exceptions.py
simple_worker/queue_providers/memory_provider.py
simple_worker/queue_providers/sqs_provider.py
tests/__init__.py
tests/test_app.py
tests/test_in_memory_provider.py
tests/test_queue.py
tests/test_sqs_provider.py
tests/test_task_executor.py
tests/test_worker.py
simple_worker-0.2.21.dist-info/METADATA
simple_worker-0.2.21.dist-info/WHEEL
simple_worker-0.2.21.dist-info/top_level.txt
simple_worker-0.2.21.dist-info/RECORD
