Metadata-Version: 2.1
Name: simple-worker
Version: 0.2.21
Summary: A task queues library that uses AWS SQS
Home-page: https://github.com/shuttl-tech/simple_worker
Author: Paul Kuruvilla
Author-email: paul.kuruvilla@shuttl.com
License: MIT
Platform: UNKNOWN
Classifier: Programming Language :: Python :: 3.7
Requires-Dist: boto3
Requires-Dist: tenacity
Provides-Extra: test
Requires-Dist: pytest ; extra == 'test'
Requires-Dist: pytest-runner ; extra == 'test'
Requires-Dist: pytest-cov ; extra == 'test'
Requires-Dist: tenacity ; extra == 'test'
